README.rst
setup.cfg
setup.py
doxygen/__init__.py
doxygen/configParser.py
doxygen/exceptions.py
doxygen/generator.py
doxygen_interface.egg-info/PKG-INFO
doxygen_interface.egg-info/SOURCES.txt
doxygen_interface.egg-info/dependency_links.txt
doxygen_interface.egg-info/top_level.txt