Metadata-Version: 1.2
Name: doxygen-interface
Version: 0.0.1
Summary: Library used to manipulate Doxygen configuration and build
Home-page: https://github.com/TraceSoftwareInternational/doxygen-python-interface
Author: Trace Software International
Author-email: open-source@trace-software.com
License: UNKNOWN
Keywords: doxygen documentation api
Platform: UNKNOWN
Classifier: Development Status :: 3 - Alpha
Classifier: Intended Audience :: Developers
Classifier: Topic :: Software Development :: Build Tools
Classifier: License :: OSI Approved :: GNU General Public License v3 (GPLv3)
Classifier: Programming Language :: Python :: 3.5
Classifier: Programming Language :: Python :: 3.6
Classifier: Programming Language :: Python :: 3.7
Classifier: Programming Language :: Python :: Implementation :: PyPy
Classifier: Topic :: Software Development :: Documentation
Requires-Python: >=3.5
